plombery/__init__.py
plombery/_version.py
plombery/api/__init__.py
plombery/api/authentication.py
plombery/api/middlewares.py
plombery/api/routers/__init__.py
plombery/api/routers/pipelines.py
plombery/api/routers/runs.py
plombery/config/__init__.py
plombery/config/model.py
plombery/config/parser.py
plombery/config/yaml_loader.py
plombery/constants.py
plombery/database/__init__.py
plombery/database/base.py
plombery/database/models.py
plombery/database/repository.py
plombery/database/schemas.py
plombery/exceptions.py
plombery/logger/__init__.py
plombery/logger/formatter.py
plombery/logger/log_record.py
plombery/logger/web_socket_handler.py
plombery/notifications/__init__.py
plombery/notifications/email_templates/images/.gitkeep
plombery/notifications/email_templates/transactional.html
plombery/notifications/helpers.py
plombery/notifications/templates.py
plombery/orchestrator/__init__.py
plombery/orchestrator/data_storage.py
plombery/orchestrator/executor.py
plombery/pipeline/__init__.py
plombery/pipeline/_utils.py
plombery/pipeline/context.py
plombery/pipeline/pipeline.py
plombery/pipeline/task.py
plombery/pipeline/trigger.py
plombery/schemas.py
plombery/static/assets/HandsonTable-BRdkCBfa.js
plombery/static/assets/HandsonTable-CeXsD9Sv.css
plombery/static/assets/index-i4Kp4-CX.js
plombery/static/assets/index-WcLCRtzS.css
plombery/static/assets/main-CTQXcDgT.js
plombery/static/assets/vendor-CXhV_CSN.js
plombery/static/index.html
plombery/static/mario-pipe-flower.png
plombery/utils.py
plombery/websocket.py
plombery_turbo-1.0.1.dist-info/LICENSE
plombery_turbo-1.0.1.dist-info/METADATA
plombery_turbo-1.0.1.dist-info/WHEEL
plombery_turbo-1.0.1.dist-info/RECORD
