Metadata-Version: 2.3
Name: plombery-turbo
Version: 1.0.1
Summary: Python task scheduler with a user-friendly web UI
License: MIT
Keywords: pipeline,task-scheduler,apscheduler,orchestrator,web-ui,fastapi,pydantic
Author: Luca Faggianelli
Author-email: luca@velvetlab.tech
Requires-Python: >=3.10
Classifier: License :: OSI Approved :: MIT License
Classifier: Programming Language :: Python :: 3
Classifier: Programming Language :: Python :: 3.10
Classifier: Programming Language :: Python :: 3.11
Classifier: Programming Language :: Python :: 3.12
Classifier: Programming Language :: Python :: 3.13
Requires-Dist: APScheduler (>=3.10.4)
Requires-Dist: SQLAlchemy (>=2.0.22)
Requires-Dist: apprise (>=1.6.0)
Requires-Dist: authlib (>=1.2.1)
Requires-Dist: fastapi (>=0.104.0)
Requires-Dist: httpx (>=0.25.0)
Requires-Dist: itsdangerous (>=2.1.2)
Requires-Dist: jinja2 (>=3.1.2)
Requires-Dist: pydantic (>=2.10.0,<3.0.0)
Requires-Dist: pydantic-settings (>=2.0.3)
Requires-Dist: python-dotenv (>=1.0.0)
Requires-Dist: python-socketio (>=5.0.0,<6.0.0)
Requires-Dist: uvicorn (>=0.23.2)
